{
  "id": "24b888c3-7cce-4c52-aab5-33db423666c1",
  "prevId": "919dd21b-3120-4eae-91ef-ef992a03d8f1",
  "version": "7",
  "dialect": "postgresql",
  "tables": {
    "public.users": {
      "name": "users",
      "schema": "",
      "columns": {
        "id": {
          "name": "id",
          "type": "uuid",
          "primaryKey": true,
          "notNull": true,
          "default": "gen_random_uuid()"
        },
        "name": {
          "name": "name",
          "type": "varchar(255)",
          "primaryKey": false,
          "notNull": false
        },
        "email": {
          "name": "email",
          "type": "varchar(255)",
          "primaryKey": false,
          "notNull": true
        },
        "plan": {
          "name": "plan",
          "type": "user_plan",
          "typeSchema": "public",
          "primaryKey": false,
          "notNull": true,
          "default": "'developer'"
        },
        "password_salt": {
          "name": "password_salt",
          "type": "text",
          "primaryKey": false,
          "notNull": false
        },
        "password_hash": {
          "name": "password_hash",
          "type": "text",
          "primaryKey": false,
          "notNull": false
        },
        "email_verified": {
          "name": "email_verified",
          "type": "boolean",
          "primaryKey": false,
          "notNull": true,
          "default": false
        },
        "verification_token": {
          "name": "verification_token",
          "type": "text",
          "primaryKey": false,
          "notNull": false
        },
        "verification_token_expires_at": {
          "name": "verification_token_expires_at",
          "type": "timestamp with time zone",
          "primaryKey": false,
          "notNull": false
        },
        "forgot_password_token": {
          "name": "forgot_password_token",
          "type": "text",
          "primaryKey": false,
          "notNull": false
        },
        "forgot_password_token_expires_at": {
          "name": "forgot_password_token_expires_at",
          "type": "timestamp with time zone",
          "primaryKey": false,
          "notNull": false
        },
        "refresh_token": {
          "name": "refresh_token",
          "type": "text",
          "primaryKey": false,
          "notNull": false
        },
        "refresh_token_salt": {
          "name": "refresh_token_salt",
          "type": "text",
          "primaryKey": false,
          "notNull": false
        },
        "refresh_token_expires_at": {
          "name": "refresh_token_expires_at",
          "type": "timestamp with time zone",
          "primaryKey": false,
          "notNull": false
        },
        "created_at": {
          "name": "created_at",
          "type": "timestamp with time zone",
          "primaryKey": false,
          "notNull": true,
          "default": "now()"
        },
        "updated_at": {
          "name": "updated_at",
          "type": "timestamp with time zone",
          "primaryKey": false,
          "notNull": true,
          "default": "now()"
        }
      },
      "indexes": {},
      "foreignKeys": {},
      "compositePrimaryKeys": {},
      "uniqueConstraints": {
        "users_email_unique": {
          "name": "users_email_unique",
          "nullsNotDistinct": false,
          "columns": [
            "email"
          ]
        }
      },
      "policies": {},
      "checkConstraints": {},
      "isRLSEnabled": false
    },
    "public.form_answers": {
      "name": "form_answers",
      "schema": "",
      "columns": {
        "id": {
          "name": "id",
          "type": "uuid",
          "primaryKey": true,
          "notNull": true,
          "default": "gen_random_uuid()"
        },
        "response_id": {
          "name": "response_id",
          "type": "uuid",
          "primaryKey": false,
          "notNull": true
        },
        "field_id": {
          "name": "field_id",
          "type": "uuid",
          "primaryKey": false,
          "notNull": true
        },
        "value": {
          "name": "value",
          "type": "jsonb",
          "primaryKey": false,
          "notNull": true
        },
        "created_at": {
          "name": "created_at",
          "type": "timestamp with time zone",
          "primaryKey": false,
          "notNull": true,
          "default": "now()"
        }
      },
      "indexes": {},
      "foreignKeys": {
        "form_answers_response_id_form_responses_id_fk": {
          "name": "form_answers_response_id_form_responses_id_fk",
          "tableFrom": "form_answers",
          "tableTo": "form_responses",
          "columnsFrom": [
            "response_id"
          ],
          "columnsTo": [
            "id"
          ],
          "onDelete": "no action",
          "onUpdate": "no action"
        },
        "form_answers_field_id_form_fields_id_fk": {
          "name": "form_answers_field_id_form_fields_id_fk",
          "tableFrom": "form_answers",
          "tableTo": "form_fields",
          "columnsFrom": [
            "field_id"
          ],
          "columnsTo": [
            "id"
          ],
          "onDelete": "no action",
          "onUpdate": "no action"
        }
      },
      "compositePrimaryKeys": {},
      "uniqueConstraints": {
        "unique_response_field": {
          "name": "unique_response_field",
          "nullsNotDistinct": false,
          "columns": [
            "response_id",
            "field_id"
          ]
        }
      },
      "policies": {},
      "checkConstraints": {},
      "isRLSEnabled": false
    },
    "public.form_field_options": {
      "name": "form_field_options",
      "schema": "",
      "columns": {
        "id": {
          "name": "id",
          "type": "uuid",
          "primaryKey": true,
          "notNull": true,
          "default": "gen_random_uuid()"
        },
        "field_id": {
          "name": "field_id",
          "type": "uuid",
          "primaryKey": false,
          "notNull": true
        },
        "label": {
          "name": "label",
          "type": "varchar(255)",
          "primaryKey": false,
          "notNull": true
        },
        "value": {
          "name": "value",
          "type": "varchar(255)",
          "primaryKey": false,
          "notNull": true
        },
        "order": {
          "name": "order",
          "type": "integer",
          "primaryKey": false,
          "notNull": true,
          "default": 1000
        },
        "created_at": {
          "name": "created_at",
          "type": "timestamp with time zone",
          "primaryKey": false,
          "notNull": true,
          "default": "now()"
        },
        "updated_at": {
          "name": "updated_at",
          "type": "timestamp with time zone",
          "primaryKey": false,
          "notNull": true,
          "default": "now()"
        }
      },
      "indexes": {},
      "foreignKeys": {
        "form_field_options_field_id_form_fields_id_fk": {
          "name": "form_field_options_field_id_form_fields_id_fk",
          "tableFrom": "form_field_options",
          "tableTo": "form_fields",
          "columnsFrom": [
            "field_id"
          ],
          "columnsTo": [
            "id"
          ],
          "onDelete": "no action",
          "onUpdate": "no action"
        }
      },
      "compositePrimaryKeys": {},
      "uniqueConstraints": {
        "unique_field_option": {
          "name": "unique_field_option",
          "nullsNotDistinct": false,
          "columns": [
            "field_id",
            "value"
          ]
        }
      },
      "policies": {},
      "checkConstraints": {},
      "isRLSEnabled": false
    },
    "public.form_fields": {
      "name": "form_fields",
      "schema": "",
      "columns": {
        "id": {
          "name": "id",
          "type": "uuid",
          "primaryKey": true,
          "notNull": true,
          "default": "gen_random_uuid()"
        },
        "form_id": {
          "name": "form_id",
          "type": "uuid",
          "primaryKey": false,
          "notNull": true
        },
        "type": {
          "name": "type",
          "type": "form_field_type",
          "typeSchema": "public",
          "primaryKey": false,
          "notNull": true
        },
        "title": {
          "name": "title",
          "type": "varchar(500)",
          "primaryKey": false,
          "notNull": true
        },
        "description": {
          "name": "description",
          "type": "text",
          "primaryKey": false,
          "notNull": false
        },
        "placeholder": {
          "name": "placeholder",
          "type": "varchar(255)",
          "primaryKey": false,
          "notNull": false
        },
        "order": {
          "name": "order",
          "type": "integer",
          "primaryKey": false,
          "notNull": true,
          "default": 1000
        },
        "validation": {
          "name": "validation",
          "type": "jsonb",
          "primaryKey": false,
          "notNull": false
        },
        "properties": {
          "name": "properties",
          "type": "jsonb",
          "primaryKey": false,
          "notNull": false
        },
        "created_at": {
          "name": "created_at",
          "type": "timestamp with time zone",
          "primaryKey": false,
          "notNull": true,
          "default": "now()"
        },
        "updated_at": {
          "name": "updated_at",
          "type": "timestamp with time zone",
          "primaryKey": false,
          "notNull": true,
          "default": "now()"
        }
      },
      "indexes": {},
      "foreignKeys": {
        "form_fields_form_id_forms_id_fk": {
          "name": "form_fields_form_id_forms_id_fk",
          "tableFrom": "form_fields",
          "tableTo": "forms",
          "columnsFrom": [
            "form_id"
          ],
          "columnsTo": [
            "id"
          ],
          "onDelete": "no action",
          "onUpdate": "no action"
        }
      },
      "compositePrimaryKeys": {},
      "uniqueConstraints": {},
      "policies": {},
      "checkConstraints": {},
      "isRLSEnabled": false
    },
    "public.form_logic_rules": {
      "name": "form_logic_rules",
      "schema": "",
      "columns": {
        "id": {
          "name": "id",
          "type": "uuid",
          "primaryKey": true,
          "notNull": true,
          "default": "gen_random_uuid()"
        },
        "form_id": {
          "name": "form_id",
          "type": "uuid",
          "primaryKey": false,
          "notNull": true
        },
        "source_field_id": {
          "name": "source_field_id",
          "type": "uuid",
          "primaryKey": false,
          "notNull": true
        },
        "target_field_id": {
          "name": "target_field_id",
          "type": "uuid",
          "primaryKey": false,
          "notNull": false
        },
        "operator": {
          "name": "operator",
          "type": "form_logic_operator",
          "typeSchema": "public",
          "primaryKey": false,
          "notNull": true
        },
        "value": {
          "name": "value",
          "type": "jsonb",
          "primaryKey": false,
          "notNull": false
        },
        "action": {
          "name": "action",
          "type": "form_logic_action",
          "typeSchema": "public",
          "primaryKey": false,
          "notNull": true
        },
        "order": {
          "name": "order",
          "type": "integer",
          "primaryKey": false,
          "notNull": true,
          "default": 1000
        },
        "created_at": {
          "name": "created_at",
          "type": "timestamp with time zone",
          "primaryKey": false,
          "notNull": true,
          "default": "now()"
        },
        "updated_at": {
          "name": "updated_at",
          "type": "timestamp with time zone",
          "primaryKey": false,
          "notNull": true,
          "default": "now()"
        }
      },
      "indexes": {},
      "foreignKeys": {
        "form_logic_rules_form_id_forms_id_fk": {
          "name": "form_logic_rules_form_id_forms_id_fk",
          "tableFrom": "form_logic_rules",
          "tableTo": "forms",
          "columnsFrom": [
            "form_id"
          ],
          "columnsTo": [
            "id"
          ],
          "onDelete": "no action",
          "onUpdate": "no action"
        },
        "form_logic_rules_source_field_id_form_fields_id_fk": {
          "name": "form_logic_rules_source_field_id_form_fields_id_fk",
          "tableFrom": "form_logic_rules",
          "tableTo": "form_fields",
          "columnsFrom": [
            "source_field_id"
          ],
          "columnsTo": [
            "id"
          ],
          "onDelete": "no action",
          "onUpdate": "no action"
        },
        "form_logic_rules_target_field_id_form_fields_id_fk": {
          "name": "form_logic_rules_target_field_id_form_fields_id_fk",
          "tableFrom": "form_logic_rules",
          "tableTo": "form_fields",
          "columnsFrom": [
            "target_field_id"
          ],
          "columnsTo": [
            "id"
          ],
          "onDelete": "no action",
          "onUpdate": "no action"
        }
      },
      "compositePrimaryKeys": {},
      "uniqueConstraints": {
        "unique_source_operator": {
          "name": "unique_source_operator",
          "nullsNotDistinct": false,
          "columns": [
            "source_field_id",
            "operator"
          ]
        }
      },
      "policies": {},
      "checkConstraints": {},
      "isRLSEnabled": false
    },
    "public.form_responses": {
      "name": "form_responses",
      "schema": "",
      "columns": {
        "id": {
          "name": "id",
          "type": "uuid",
          "primaryKey": true,
          "notNull": true,
          "default": "gen_random_uuid()"
        },
        "form_id": {
          "name": "form_id",
          "type": "uuid",
          "primaryKey": false,
          "notNull": true
        },
        "respondent_user_id": {
          "name": "respondent_user_id",
          "type": "uuid",
          "primaryKey": false,
          "notNull": false
        },
        "respondent_email": {
          "name": "respondent_email",
          "type": "varchar(255)",
          "primaryKey": false,
          "notNull": false
        },
        "is_anonymous": {
          "name": "is_anonymous",
          "type": "boolean",
          "primaryKey": false,
          "notNull": true,
          "default": true
        },
        "metadata": {
          "name": "metadata",
          "type": "jsonb",
          "primaryKey": false,
          "notNull": false
        },
        "submitted_at": {
          "name": "submitted_at",
          "type": "timestamp with time zone",
          "primaryKey": false,
          "notNull": true,
          "default": "now()"
        },
        "created_at": {
          "name": "created_at",
          "type": "timestamp with time zone",
          "primaryKey": false,
          "notNull": true,
          "default": "now()"
        }
      },
      "indexes": {},
      "foreignKeys": {
        "form_responses_form_id_forms_id_fk": {
          "name": "form_responses_form_id_forms_id_fk",
          "tableFrom": "form_responses",
          "tableTo": "forms",
          "columnsFrom": [
            "form_id"
          ],
          "columnsTo": [
            "id"
          ],
          "onDelete": "no action",
          "onUpdate": "no action"
        },
        "form_responses_respondent_user_id_users_id_fk": {
          "name": "form_responses_respondent_user_id_users_id_fk",
          "tableFrom": "form_responses",
          "tableTo": "users",
          "columnsFrom": [
            "respondent_user_id"
          ],
          "columnsTo": [
            "id"
          ],
          "onDelete": "no action",
          "onUpdate": "no action"
        }
      },
      "compositePrimaryKeys": {},
      "uniqueConstraints": {},
      "policies": {},
      "checkConstraints": {},
      "isRLSEnabled": false
    },
    "public.forms": {
      "name": "forms",
      "schema": "",
      "columns": {
        "id": {
          "name": "id",
          "type": "uuid",
          "primaryKey": true,
          "notNull": true,
          "default": "gen_random_uuid()"
        },
        "creator_id": {
          "name": "creator_id",
          "type": "uuid",
          "primaryKey": false,
          "notNull": true
        },
        "title": {
          "name": "title",
          "type": "varchar(255)",
          "primaryKey": false,
          "notNull": true
        },
        "description": {
          "name": "description",
          "type": "text",
          "primaryKey": false,
          "notNull": false
        },
        "slug": {
          "name": "slug",
          "type": "varchar(255)",
          "primaryKey": false,
          "notNull": true
        },
        "status": {
          "name": "status",
          "type": "form_status",
          "typeSchema": "public",
          "primaryKey": false,
          "notNull": true,
          "default": "'draft'"
        },
        "visibility": {
          "name": "visibility",
          "type": "form_visibility",
          "typeSchema": "public",
          "primaryKey": false,
          "notNull": true,
          "default": "'unlisted'"
        },
        "access_mode": {
          "name": "access_mode",
          "type": "form_access_mode",
          "typeSchema": "public",
          "primaryKey": false,
          "notNull": true,
          "default": "'public'"
        },
        "allow_anonymous_responses": {
          "name": "allow_anonymous_responses",
          "type": "boolean",
          "primaryKey": false,
          "notNull": true,
          "default": true
        },
        "allow_multiple_responses": {
          "name": "allow_multiple_responses",
          "type": "boolean",
          "primaryKey": false,
          "notNull": true,
          "default": true
        },
        "password_salt": {
          "name": "password_salt",
          "type": "text",
          "primaryKey": false,
          "notNull": false
        },
        "password_hash": {
          "name": "password_hash",
          "type": "text",
          "primaryKey": false,
          "notNull": false
        },
        "result_visibility": {
          "name": "result_visibility",
          "type": "form_result_visibility",
          "typeSchema": "public",
          "primaryKey": false,
          "notNull": true,
          "default": "'creator_only'"
        },
        "show_individual_submission": {
          "name": "show_individual_submission",
          "type": "boolean",
          "primaryKey": false,
          "notNull": true,
          "default": false
        },
        "show_aggregate_summary": {
          "name": "show_aggregate_summary",
          "type": "boolean",
          "primaryKey": false,
          "notNull": true,
          "default": false
        },
        "show_charts": {
          "name": "show_charts",
          "type": "boolean",
          "primaryKey": false,
          "notNull": true,
          "default": false
        },
        "collect_email": {
          "name": "collect_email",
          "type": "boolean",
          "primaryKey": false,
          "notNull": true,
          "default": false
        },
        "show_progress_bar": {
          "name": "show_progress_bar",
          "type": "boolean",
          "primaryKey": false,
          "notNull": true,
          "default": true
        },
        "shuffle_fields": {
          "name": "shuffle_fields",
          "type": "boolean",
          "primaryKey": false,
          "notNull": true,
          "default": false
        },
        "redirect_url": {
          "name": "redirect_url",
          "type": "text",
          "primaryKey": false,
          "notNull": false
        },
        "thank_you_message": {
          "name": "thank_you_message",
          "type": "text",
          "primaryKey": false,
          "notNull": false
        },
        "settings": {
          "name": "settings",
          "type": "jsonb",
          "primaryKey": false,
          "notNull": false
        },
        "view_count": {
          "name": "view_count",
          "type": "integer",
          "primaryKey": false,
          "notNull": true,
          "default": 0
        },
        "start_count": {
          "name": "start_count",
          "type": "integer",
          "primaryKey": false,
          "notNull": true,
          "default": 0
        },
        "published_at": {
          "name": "published_at",
          "type": "timestamp with time zone",
          "primaryKey": false,
          "notNull": false
        },
        "created_at": {
          "name": "created_at",
          "type": "timestamp with time zone",
          "primaryKey": false,
          "notNull": true,
          "default": "now()"
        },
        "updated_at": {
          "name": "updated_at",
          "type": "timestamp with time zone",
          "primaryKey": false,
          "notNull": true,
          "default": "now()"
        }
      },
      "indexes": {},
      "foreignKeys": {
        "forms_creator_id_users_id_fk": {
          "name": "forms_creator_id_users_id_fk",
          "tableFrom": "forms",
          "tableTo": "users",
          "columnsFrom": [
            "creator_id"
          ],
          "columnsTo": [
            "id"
          ],
          "onDelete": "no action",
          "onUpdate": "no action"
        }
      },
      "compositePrimaryKeys": {},
      "uniqueConstraints": {
        "unique_create_and_slug": {
          "name": "unique_create_and_slug",
          "nullsNotDistinct": false,
          "columns": [
            "creator_id",
            "slug"
          ]
        }
      },
      "policies": {},
      "checkConstraints": {},
      "isRLSEnabled": false
    }
  },
  "enums": {
    "public.user_plan": {
      "name": "user_plan",
      "schema": "public",
      "values": [
        "developer",
        "pro"
      ]
    },
    "public.form_access_mode": {
      "name": "form_access_mode",
      "schema": "public",
      "values": [
        "public",
        "authenticated"
      ]
    },
    "public.form_field_type": {
      "name": "form_field_type",
      "schema": "public",
      "values": [
        "short_text",
        "long_text",
        "email",
        "phone",
        "number",
        "url",
        "date",
        "time",
        "multiple_choice",
        "checkboxes",
        "dropdown",
        "rating",
        "opinion_scale",
        "yes_no",
        "file_upload",
        "statement"
      ]
    },
    "public.form_logic_action": {
      "name": "form_logic_action",
      "schema": "public",
      "values": [
        "show",
        "hide",
        "jump_to",
        "end_form"
      ]
    },
    "public.form_logic_operator": {
      "name": "form_logic_operator",
      "schema": "public",
      "values": [
        "equals",
        "not_equals",
        "contains",
        "not_contains",
        "greater_than",
        "less_than",
        "is_empty",
        "is_not_empty"
      ]
    },
    "public.form_result_visibility": {
      "name": "form_result_visibility",
      "schema": "public",
      "values": [
        "hidden",
        "after_submit",
        "creator_only"
      ]
    },
    "public.form_status": {
      "name": "form_status",
      "schema": "public",
      "values": [
        "draft",
        "published",
        "archived"
      ]
    },
    "public.form_visibility": {
      "name": "form_visibility",
      "schema": "public",
      "values": [
        "listed",
        "unlisted"
      ]
    }
  },
  "schemas": {},
  "sequences": {},
  "roles": {},
  "policies": {},
  "views": {},
  "_meta": {
    "columns": {},
    "schemas": {},
    "tables": {}
  }
}